{
  "$schema": "http://json-schema.org/draft-07/schema#",
  "type": "object",
  "title": "Klantcontact",
  "description": "Represents a Klantcontact in the system",
  "properties": {
    "eindtijd": {
      "description": "Property eindtijd",
      "type": "string",
      "format": "date-time"
    },
    "kanaal": {
      "description": "Property kanaal",
      "type": "string"
    },
    "notitie": {
      "description": "Property notitie",
      "type": "string"
    },
    "starttijd": {
      "description": "Property starttijd",
      "type": "string",
      "format": "date-time"
    },
    "tijdsduur": {
      "description": "Property tijdsduur",
      "type": "string"
    },
    "toelichting": {
      "description": "Property toelichting",
      "type": "string"
    },
    "wachttijdTotaal": {
      "description": "Property wachttijdTotaal",
      "type": "string"
    }
  }
}