{
  "$schema": "http://json-schema.org/draft-07/schema#",
  "type": "object",
  "title": "Zaak",
  "description": "Represents a Zaak in the system",
  "properties": {
    "archiefnominatie": {
      "description": "Property archiefnominatie",
      "type": "string"
    },
    "datumEinde": {
      "description": "Property datumEinde",
      "type": "string"
    },
    "datumEindeGepland": {
      "description": "Property datumEindeGepland",
      "type": "string"
    },
    "datumEindeUiterlijkeAfdoening": {
      "description": "Property datumEindeUiterlijkeAfdoening",
      "type": "string"
    },
    "datumLaatsteBetaling": {
      "description": "Property datumLaatsteBetaling",
      "type": "string"
    },
    "datumPublicatie": {
      "description": "Property datumPublicatie",
      "type": "string"
    },
    "datumRegistratie": {
      "description": "Property datumRegistratie",
      "type": "string"
    },
    "datumStart": {
      "description": "Property datumStart",
      "type": "string"
    },
    "datumVernietigingDossier": {
      "description": "Property datumVernietigingDossier",
      "type": "string"
    },
    "document": {
      "description": "Property document",
      "type": "string"
    },
    "duurVerlenging": {
      "description": "Property duurVerlenging",
      "type": "string"
    },
    "indicatieBetaling": {
      "description": "Property indicatieBetaling",
      "type": "string"
    },
    "indicatieDeelzaken": {
      "description": "Property indicatieDeelzaken",
      "type": "string"
    },
    "indicatieOpschorting": {
      "description": "Property indicatieOpschorting",
      "type": "string"
    },
    "leges": {
      "description": "Property leges",
      "type": "string"
    },
    "omschrijving": {
      "description": "Property omschrijving",
      "type": "string"
    },
    "omschrijvingResultaat": {
      "description": "Property omschrijvingResultaat",
      "type": "string"
    },
    "redenOpschorting": {
      "description": "Property redenOpschorting",
      "type": "string"
    },
    "redenVerlenging": {
      "description": "Property redenVerlenging",
      "type": "string"
    },
    "toelichting": {
      "description": "Property toelichting",
      "type": "string"
    },
    "toelichtingResultaat": {
      "description": "Property toelichtingResultaat",
      "type": "string"
    },
    "vertrouwelijkheid": {
      "description": "Property vertrouwelijkheid",
      "type": "string"
    },
    "zaakidentificatie": {
      "description": "Property zaakidentificatie",
      "type": "string"
    },
    "zaakniveau": {
      "description": "Property zaakniveau",
      "type": "string"
    },
    "type": {
      "description": "Property type",
      "type": "string"
    },
    "status": {
      "description": "Property status",
      "type": "string"
    }
  }
}